qsaas
