Metadata-Version: 2.1
Name: qsaas
Version: 1.1.1
Summary: A Python wrapper for the Qlik Sense Enterprise SaaS APIs.
Home-page: https://github.com/eapowertools/qsaas
Author: Daniel Pilla
Author-email: daniel.b.pilla@gmail.com
License: GPL-3.0
Download-URL: https://github.com/eapowertools/qsaas/archive/v1.1.1.tar.gz
Keywords: Qlik,API,REST,Sense,QSAAS,QSESAAS
Platform: UNKNOWN
Classifier: Development Status :: 5 - Production/Stable
Classifier: Intended Audience :: Developers
Classifier: License :: OSI Approved :: GNU General Public License v3 (GPLv3)
Classifier: Programming Language :: Python :: 3.5
Classifier: Programming Language :: Python :: 3.6
Classifier: Programming Language :: Python :: 3.7
Requires-Python: >=3.5
